alglab/__init__.py
alglab/dataset.py
alglab/evaluation.py
alglab/experiment.py
alglab/results.py
alglab-1.2.1.dist-info/METADATA
alglab-1.2.1.dist-info/WHEEL
alglab-1.2.1.dist-info/licenses/LICENSE
alglab-1.2.1.dist-info/RECORD
